binomial_gaussian_distributions_kb
