Metadata-Version: 1.0
Name: binomial-gaussian-distributions-kb
Version: 1.0.2
Summary: Binomial and Gaussian distributions
Home-page: UNKNOWN
Author: Kenneth Bundy
Author-email: kennybcuz@gmail.com
License: UNKNOWN
Platform: UNKNOWN
